{"status":"done","publicPath":"http://127.0.0.1:8080/","chunks":{"app":[{"name":"bundle.js","publicPath":"http://127.0.0.1:8080/bundle.js","path":"C:\\Users\\monde\\projects\\e_wallet\\frontend\\dist\\bundle.js"},{"name":"app.a75844bb364dfd6cacc1.hot-update.js","publicPath":"http://127.0.0.1:8080/app.a75844bb364dfd6cacc1.hot-update.js","path":"C:\\Users\\monde\\projects\\e_wallet\\frontend\\dist\\app.a75844bb364dfd6cacc1.hot-update.js"}]},"error":"ModuleNotFoundError","message":"Module not found: Error: Can't resolve '@/common/apiService.js' in 'C:\\Users\\monde\\projects\\e_wallet\\frontend\\src\\views'"}